alphaavatar/agents/__init__.py
alphaavatar/agents/constants.py
alphaavatar/agents/log.py
alphaavatar/agents/plugin.py
alphaavatar/agents/version.py
alphaavatar/agents/avatar/__init__.py
alphaavatar/agents/avatar/engine.py
alphaavatar/agents/avatar/context/__init__.py
alphaavatar/agents/avatar/context/context_manager.py
alphaavatar/agents/avatar/context/template.py
alphaavatar/agents/avatar/context/enum/op.py
alphaavatar/agents/avatar/context/prompts/avatar_system_prompts.py
alphaavatar/agents/avatar/context/prompts/plugins_memory_prompts.py
alphaavatar/agents/avatar/patches/__init__.py
alphaavatar/agents/avatar/patches/context_search_patch.py
alphaavatar/agents/avatar/patches/worker_patch.py
alphaavatar/agents/configs/__init__.py
alphaavatar/agents/configs/avatar_config.py
alphaavatar/agents/configs/avatar_info_config.py
alphaavatar/agents/configs/parser.py
alphaavatar/agents/configs/session_config.py
alphaavatar/agents/configs/plugins/character_plugin_config.py
alphaavatar/agents/configs/plugins/livekit_plugin_config.py
alphaavatar/agents/configs/plugins/memory_plugin_config.py
alphaavatar/agents/configs/plugins/persona_plugin_config.py
alphaavatar/agents/configs/plugins/tools_plugin_config.py
alphaavatar/agents/entrypoints/main.py
alphaavatar/agents/memory/__init__.py
alphaavatar/agents/memory/base.py
alphaavatar/agents/memory/cache.py
alphaavatar/agents/memory/schema/memory_item.py
alphaavatar/agents/memory/schema/memory_type.py
alphaavatar/agents/memory/schema/runner_op.py
alphaavatar/agents/persona/__init__.py
alphaavatar/agents/persona/base.py
alphaavatar/agents/persona/cache.py
alphaavatar/agents/persona/face.py
alphaavatar/agents/persona/profiler.py
alphaavatar/agents/persona/speaker.py
alphaavatar/agents/persona/schema/runner_op.py
alphaavatar/agents/persona/schema/user_profile.py
alphaavatar/agents/reflection/__init__.py
alphaavatar/agents/sessions/__init__.py
alphaavatar/agents/sessions/character_session.py
alphaavatar/agents/tools/__init__.py
alpha_avatar_agents-0.4.0.dist-info/METADATA
alpha_avatar_agents-0.4.0.dist-info/WHEEL
alpha_avatar_agents-0.4.0.dist-info/entry_points.txt
alpha_avatar_agents-0.4.0.dist-info/RECORD
