Metadata-Version: 2.4
Name: alpha-avatar-agents
Version: 0.4.0
Summary: A real-time interactive Omni Avatar Agent built on LiveKit.
Project-URL: Source, https://github.com/AlphaAvatar/AlphaAvatar
License-Expression: Apache-2.0
Keywords: AI,agents,audio,llm,omni,realtime,video
Classifier: Intended Audience :: Developers
Classifier: License :: OSI Approved :: Apache Software License
Classifier: Programming Language :: Python :: 3
Classifier: Programming Language :: Python :: 3 :: Only
Classifier: Programming Language :: Python :: 3.10
Classifier: Programming Language :: Python :: 3.11
Classifier: Programming Language :: Python :: 3.12
Classifier: Programming Language :: Python :: 3.13
Classifier: Topic :: Multimedia :: Sound/Audio
Classifier: Topic :: Multimedia :: Video
Classifier: Topic :: Scientific/Engineering :: Artificial Intelligence
Requires-Python: >=3.10
Requires-Dist: alpha-avatar-plugins-memory>=0.1.0
Requires-Dist: alpha-avatar-plugins-persona>=0.1.0
Requires-Dist: livekit-agents~=1.0
Requires-Dist: livekit-api<2,>=1.0.4
Requires-Dist: livekit-blingfire~=1.0
Requires-Dist: livekit-plugins-noise-cancellation~=0.2
Requires-Dist: livekit-plugins-openai>=1.2.4
Requires-Dist: livekit-plugins-silero>=1.2.5
Requires-Dist: livekit-plugins-turn-detector>=1.2.4
Requires-Dist: livekit-protocol~=1.0
Requires-Dist: livekit<2,>=1.0.12
Requires-Dist: markdown
Requires-Dist: mcp<2,>=1.10.0
Requires-Dist: omegaconf
Requires-Dist: python-dotenv
Requires-Dist: python-slugify
Requires-Dist: weasyprint
Provides-Extra: character
Requires-Dist: alpha-avatar-plugins-character>=0.1.0; extra == 'character'
Provides-Extra: tools
Requires-Dist: alpha-avatar-plugins-deepresearch>=0.1.0; extra == 'tools'
Requires-Dist: alpha-avatar-plugins-rag>=0.1.0; extra == 'tools'
